{
  "check_1_structure": {
    "app.py": true,
    "requirements.txt": true,
    "README.md": true,
    "src/train_model.py": true,
    "src/predict.py": true,
    "src/check_setup.py": true,
    "src/config.json": true,
    "data/email.csv": true,
    "models/README.md": true
  },
  "check_1_all_required_files_present": true,
  "check_2_python_syntax": {
    "app.py": true,
    "src/train_model.py": true,
    "src/predict.py": true,
    "src/check_setup.py": true
  },
  "check_2_all_python_files_compile": true,
  "check_2_config_loads": true,
  "check_2_csv_has_required_columns": true,
  "csv_shape": [
    5171,
    4
  ],
  "csv_columns": [
    "Unnamed: 0",
    "label",
    "text",
    "label_num"
  ],
  "note": "TensorFlow is not installed in this environment, so runtime training was not executed here. The files are ready to run after pip install -r requirements.txt."
}